qiskit_addon_opt_mapper/VERSION.txt
qiskit_addon_opt_mapper/__init__.py
qiskit_addon_opt_mapper/exceptions.py
qiskit_addon_opt_mapper/infinity.py
qiskit_addon_opt_mapper/optionals.py
qiskit_addon_opt_mapper/applications/__init__.py
qiskit_addon_opt_mapper/applications/bin_packing.py
qiskit_addon_opt_mapper/applications/clique.py
qiskit_addon_opt_mapper/applications/exact_cover.py
qiskit_addon_opt_mapper/applications/graph_optimization_application.py
qiskit_addon_opt_mapper/applications/graph_partition.py
qiskit_addon_opt_mapper/applications/independent_set.py
qiskit_addon_opt_mapper/applications/knapsack.py
qiskit_addon_opt_mapper/applications/max_cut.py
qiskit_addon_opt_mapper/applications/number_partition.py
qiskit_addon_opt_mapper/applications/optimization_application.py
qiskit_addon_opt_mapper/applications/set_packing.py
qiskit_addon_opt_mapper/applications/sk_model.py
qiskit_addon_opt_mapper/applications/tsp.py
qiskit_addon_opt_mapper/applications/vehicle_routing.py
qiskit_addon_opt_mapper/applications/vertex_cover.py
qiskit_addon_opt_mapper/converters/__init__.py
qiskit_addon_opt_mapper/converters/binary_to_spin.py
qiskit_addon_opt_mapper/converters/equality_to_penalty.py
qiskit_addon_opt_mapper/converters/flip_problem_sense.py
qiskit_addon_opt_mapper/converters/inequality_to_equality.py
qiskit_addon_opt_mapper/converters/integer_to_binary.py
qiskit_addon_opt_mapper/converters/linear_inequality_to_penalty.py
qiskit_addon_opt_mapper/converters/optimization_problem_converter.py
qiskit_addon_opt_mapper/converters/optimization_problem_to_hubo.py
qiskit_addon_opt_mapper/converters/optimization_problem_to_qubo.py
qiskit_addon_opt_mapper/converters/spin_to_binary.py
qiskit_addon_opt_mapper/converters/util.py
qiskit_addon_opt_mapper/problems/__init__.py
qiskit_addon_opt_mapper/problems/constraint.py
qiskit_addon_opt_mapper/problems/higher_order_constraint.py
qiskit_addon_opt_mapper/problems/higher_order_expression.py
qiskit_addon_opt_mapper-0.1.0.dist-info/METADATA
qiskit_addon_opt_mapper-0.1.0.dist-info/WHEEL
qiskit_addon_opt_mapper-0.1.0.dist-info/licenses/LICENSE.txt
qiskit_addon_opt_mapper-0.1.0.dist-info/RECORD
